quicklines/__init__.py
quicklines/quicklines.py
quicklines/quicklines_logo.png
quicklines-1.0.1.dist-info/LICENSE
quicklines-1.0.1.dist-info/METADATA
quicklines-1.0.1.dist-info/WHEEL
quicklines-1.0.1.dist-info/RECORD
