Metadata-Version: 2.1
Name: quicklines
Version: 1.0.1
Summary: A simple package that will extract emission line profile information given a 1D spectra of a galaxy
License: LICENSE
Author: Ali Ahmad Khostovan
Author-email: akhostov@gmail.com
Requires-Python: >=3.8,<4.0
Classifier: License :: Other/Proprietary License
Classifier: Programming Language :: Python :: 3
Classifier: Programming Language :: Python :: 3.8
Classifier: Programming Language :: Python :: 3.9
Classifier: Programming Language :: Python :: 3.10
Classifier: Programming Language :: Python :: 3.11
Classifier: Programming Language :: Python :: 3.12
